{"adult":false,"backdrop_path":"/kGOuFe4EJKBcgj4VPodYTFuDAFY.jpg","belongs_to_collection":null,"budget":25000000,"genres":[{"id":27,"name":"Horror"},{"id":35,"name":"Comedy"},{"id":10402,"name":"Music"}],"homepage":"","id":10776,"imdb_id":"tt0091419","original_language":"en","original_title":"Little Shop of Horrors","overview":"Seymour Krelborn is a nerdy orphan working at Mushnik's, a flower shop in urban Skid Row. He harbors a crush on fellow co-worker Audrey Fulquard, and is berated by Mr. Mushnik daily. One day as Seymour is seeking a new mysterious plant, he finds a very mysterious unidentified plant which he calls Audrey II. The plant seems to have a craving for blood and soon begins to sing for his supper.","popularity":0.6963,"poster_path":"/bxRm8F7rnCsVDyrNh3K9yIFFBKL.jpg","production_companies":[{"name":"Geffen Company, The","id":4354},{"name":"Warner Bros.","id":6194}],"production_countries":[{"iso_3166_1":"US","name":"United States of America"}],"release_date":"1986-12-19","revenue":38748395,"runtime":94,"spoken_languages":[{"iso_639_1":"en","name":"English"}],"status":"Released","tagline":"Don't feed the plants.","title":"Little Shop of Horrors","video":false,"vote_average":6.6,"vote_count":323,"credits":{"cast":[{"cast_id":8,"character":"Seymour Krelborn","credit_id":"52fe43b59251416c7501b051","id":8872,"name":"Rick Moranis","order":0,"profile_path":"/rVZbTJjM4g0Um6trlLHRiBzBO7t.jpg"},{"cast_id":9,"character":"Audrey","credit_id":"52fe43b59251416c7501b055","id":13420,"name":"Ellen Greene","order":1,"profile_path":"/1EHwrl4PzPJzVbheXoqW6uzhMos.jpg"},{"cast_id":10,"character":"Mr. Mushnik","credit_id":"52fe43b59251416c7501b059","id":14830,"name":"Vincent Gardenia","order":2,"profile_path":"/g7iwqHaaIKh5lSTW39pXT0OOXVC.jpg"},{"cast_id":11,"character":"Orin Scrivello, DDS","credit_id":"52fe43b59251416c7501b05d","id":67773,"name":"Steve Martin","order":3,"profile_path":"/rI2EMvkfKKPKa5z0nM2pFVBtUyO.jpg"},{"cast_id":12,"character":"Chiffon","credit_id":"52fe43b59251416c7501b061","id":141823,"name":"Tisha Campbell-Martin","order":4,"profile_path":"/8nfymZ8Ohi7P5mNGOMddRmm5pgF.jpg"},{"cast_id":14,"character":"Wink Wilkinson","credit_id":"52fe43b59251416c7501b069","id":7180,"name":"John Candy","order":5,"profile_path":"/a53ilUnwQ4q7sM0F0h14dbunKA7.jpg"},{"cast_id":15,"character":"Arthur Denton","credit_id":"52fe43b59251416c7501b06d","id":1532,"name":"Bill Murray","order":6,"profile_path":"/7BOoOAIA1CnSzFSVSJP7saniQaB.jpg"},{"cast_id":22,"character":"Crystal","credit_id":"56952080c3a3680e9d0022c8","id":83600,"name":"Tichina Arnold","order":7,"profile_path":"/A9L6I9tzUg0FSl626JMtMuDodZc.jpg"},{"cast_id":16,"character":"Dental Nurse","credit_id":"530711f6c3a3685181000043","id":6199,"name":"Miriam Margolyes","order":8,"profile_path":"/7Fijg5sZ7gKbooq6tId3MUS5sDY.jpg"},{"cast_id":17,"character":"Partick Martin","credit_id":"54091885c3a36812cd000992","id":26485,"name":"Jim Belushi","order":9,"profile_path":"/AplV1ikSo3Zn93hhy5ht7Y7sQio.jpg"},{"cast_id":21,"character":"The First Customer","credit_id":"569520379251414b740025f6","id":13524,"name":"Christopher Guest","order":10,"profile_path":"/fhEQq0q2aR2sh4HU824xunoyAce.jpg"},{"cast_id":23,"character":"Doo-Wop Street Singer","credit_id":"569520dfc3a3680e9a002497","id":115787,"name":"Danny John-Jules","order":11,"profile_path":"/d9yIjilG7BdiPYIsXyZBV0hCuyv.jpg"},{"cast_id":24,"character":"Doo-Wop Street Singer","credit_id":"5695210c9251417fd1000315","id":102757,"name":"Mak Wilson","order":12,"profile_path":"/i0sbuTMlkTXiEmzVnyY8GvdZykZ.jpg"},{"cast_id":25,"character":"Fifth Customer","credit_id":"56952162c3a3680e9f00239b","id":1353187,"name":"Barbara Rosenblat","order":13,"profile_path":"/62ABagBserEa6xtNG2u0fpUEBmD.jpg"},{"cast_id":26,"character":"Fourth Customer","credit_id":"56952446c3a3680ea80029a1","id":1330820,"name":"Kevin Scott","order":14,"profile_path":"/jx50f8hlEfBPUQqDZlukoyujC2m.jpg"},{"cast_id":27,"character":"Chinese Florist","credit_id":"57f7fd6ac3a368240d003afe","id":1257821,"name":"Vincent Wong","order":15,"profile_path":"/r09FygOv9rWFFNtT2FcRepS6v1y.jpg"},{"cast_id":13,"character":"Audrey II (Voice)","credit_id":"52fe43b59251416c7501b065","id":218028,"name":"Levi Stubbs","order":16,"profile_path":null}],"crew":[{"credit_id":"52fe43b59251416c7501b029","department":"Directing","id":7908,"job":"Director","name":"Frank Oz","profile_path":"/9KqCa2wS4EO2yymrVIgMiFHh6M4.jpg"},{"credit_id":"52fe43b59251416c7501b02f","department":"Writing","id":52140,"job":"Screenplay","name":"Charles B. Griffith","profile_path":null},{"credit_id":"52fe43b59251416c7501b035","department":"Writing","id":62049,"job":"Musical","name":"Howard Ashman","profile_path":"/cFFiTRB1OBacqzDmiu128mvijdB.jpg"},{"credit_id":"52fe43b59251416c7501b03b","department":"Production","id":9020,"job":"Producer","name":"David Geffen","profile_path":null},{"credit_id":"52fe43b59251416c7501b041","department":"Sound","id":63964,"job":"Original Music Composer","name":"Miles Goodman","profile_path":null},{"credit_id":"52fe43b59251416c7501b047","department":"Camera","id":14456,"job":"Director of Photography","name":"Robert Paynter","profile_path":null},{"credit_id":"52fe43b59251416c7501b04d","department":"Editing","id":7754,"job":"Editor","name":"John Jympson","profile_path":null},{"credit_id":"558d5ce3c3a3687bde0003c1","department":"Production","id":6347,"job":"Casting","name":"Margery Simkin","profile_path":"/dCyAWZGEaW1OlGgh5ALiqGfsbpb.jpg"},{"credit_id":"558d5d0ec3a36834820001e0","department":"Art","id":5022,"job":"Production Design","name":"Roy Walker","profile_path":null},{"credit_id":"558d5d4b9251411bc40001a6","department":"Costume & Make-Up","id":11714,"job":"Costume Design","name":"Marit Allen","profile_path":null}]},"release_dates":{"results":[{"iso_3166_1":"AU","release_dates":[{"certification":"M","iso_639_1":"en","release_date":"1987-03-19T00:00:00.000Z","type":3}]},{"iso_3166_1":"BR","release_dates":[{"certification":"12","iso_639_1":"","release_date":"1986-12-19T00:00:00.000Z","type":3}]},{"iso_3166_1":"FR","release_dates":[{"certification":"","iso_639_1":"","note":"","release_date":"1987-06-03T00:00:00.000Z","type":3}]},{"iso_3166_1":"DE","release_dates":[{"certification":"12","iso_639_1":"","note":"","release_date":"1987-05-13T00:00:00.000Z","type":3}]},{"iso_3166_1":"GR","release_dates":[{"certification":"13","iso_639_1":"","note":"","release_date":"1987-09-12T00:00:00.000Z","type":3}]},{"iso_3166_1":"GB","release_dates":[{"certification":"PG","iso_639_1":"","note":"","release_date":"1987-03-26T00:00:00.000Z","type":3}]},{"iso_3166_1":"US","release_dates":[{"certification":"PG-13","iso_639_1":"","note":"","release_date":"1986-12-19T00:00:00.000Z","type":3}]}]},"alternative_titles":{"titles":[{"iso_3166_1":"ES","title":"La tienda de los horrores"}]},"translations":{"translations":[{"iso_639_1":"it","iso_3166_1":"IT","name":"Italiano","english_name":"Italian"},{"iso_639_1":"en","iso_3166_1":"US","name":"English","english_name":"English"},{"iso_639_1":"de","iso_3166_1":"DE","name":"Deutsch","english_name":"German"},{"iso_639_1":"fr","iso_3166_1":"FR","name":"Français","english_name":"French"},{"iso_639_1":"cs","iso_3166_1":"CZ","name":"Český","english_name":"Czech"},{"iso_639_1":"sv","iso_3166_1":"SE","name":"svenska","english_name":"Swedish"},{"iso_639_1":"nl","iso_3166_1":"NL","name":"Nederlands","english_name":"Dutch"},{"iso_639_1":"pt","iso_3166_1":"PT","name":"Português","english_name":"Portuguese"},{"iso_639_1":"hu","iso_3166_1":"HU","name":"Magyar","english_name":"Hungarian"},{"iso_639_1":"el","iso_3166_1":"GR","name":"ελληνικά","english_name":"Greek"},{"iso_639_1":"he","iso_3166_1":"IL","name":"עִבְרִית","english_name":"Hebrew"},{"iso_639_1":"da","iso_3166_1":"DK","name":"Dansk","english_name":"Danish"},{"iso_639_1":"es","iso_3166_1":"ES","name":"Español","english_name":"Spanish"},{"iso_639_1":"ru","iso_3166_1":"RU","name":"Pусский","english_name":"Russian"},{"iso_639_1":"tr","iso_3166_1":"TR","name":"Türkçe","english_name":"Turkish"},{"iso_639_1":"zh","iso_3166_1":"CN","name":"普通话","english_name":"Mandarin"},{"iso_639_1":"pt","iso_3166_1":"BR","name":"Português","english_name":"Portuguese"}]},"keywords":{"keywords":[{"id":2382,"name":"flower"},{"id":2642,"name":"solar eclipse"},{"id":2778,"name":"florist"},{"id":3487,"name":"assistant"},{"id":3704,"name":"plants"},{"id":3836,"name":"success"},{"id":4015,"name":"aggression by plant"},{"id":5340,"name":"investigation"},{"id":5801,"name":"nerd"},{"id":6946,"name":"blonde"},{"id":8183,"name":"carnivorous plant"},{"id":9714,"name":"remake"},{"id":9986,"name":"crush"},{"id":10181,"name":"based on play"},{"id":14735,"name":"motorcycle"},{"id":14773,"name":"eclipse"},{"id":33491,"name":"part animated"},{"id":33780,"name":"dentist"},{"id":41267,"name":"bum"},{"id":155806,"name":"killer plant"},{"id":158375,"name":"based on stage musical"},{"id":165314,"name":"skid row"},{"id":165317,"name":"based on film"},{"id":165319,"name":"plant food"},{"id":165324,"name":"flesh eating plant"},{"id":165334,"name":"inept assistant"},{"id":165580,"name":"cult classic"},{"id":210234,"name":"man eating plant"}]}}