{"adult":false,"backdrop_path":"/8aTlZi1TDXDSIoIsNPXxTEJxBIG.jpg","belongs_to_collection":null,"budget":150,"genres":[{"id":27,"name":"Horror"}],"homepage":"","id":122326,"imdb_id":"tt2297108","original_language":"en","original_title":"100 Ghost Street: The Return of Richard Speck","overview":"A group of paranormal investigators sojourned to the Chicago walk-up where deranged drifter Richard Speck systematically slew eight student nurses back in ’66, looking for restless spirits. Their unfortunate success gets shockingly documented in this fear-filled found-footage foray featuring a bright young cast.","popularity":0.083428,"poster_path":"/hA7QgiTDthevcFjcmQXlu3bjPA3.jpg","production_companies":[{"name":"Asylum","id":6306}],"production_countries":[{"iso_3166_1":"US","name":"United States of America"}],"release_date":"2012-07-24","revenue":0,"runtime":84,"spoken_languages":[{"iso_639_1":"en","name":"English"}],"status":"Released","tagline":"","title":"100 Ghost Street: The Return of Richard Speck","video":false,"vote_average":4.9,"vote_count":7,"credits":{"cast":[{"cast_id":1,"character":"Jackie","credit_id":"52fe4a7bc3a368484e155cb1","id":1077737,"name":"Jackie Moore","order":0,"profile_path":"/40JBGG7xYAMqBr5t0oOAMiRtVqW.jpg"},{"cast_id":3,"character":"Jen","credit_id":"52fe4a7bc3a368484e155cb5","id":1131066,"name":"Jennifer Robyn Jacobs","order":1,"profile_path":null}],"crew":[]},"release_dates":{"results":[{"iso_3166_1":"US","release_dates":[{"certification":"","iso_639_1":"","note":"","release_date":"2012-07-24T00:00:00.000Z","type":3}]}]},"alternative_titles":{"titles":[{"iso_3166_1":"AU","title":"100 Ghost Street"}]},"translations":{"translations":[{"iso_639_1":"en","iso_3166_1":"US","name":"English","english_name":"English"},{"iso_639_1":"de","iso_3166_1":"DE","name":"Deutsch","english_name":"German"},{"iso_639_1":"nl","iso_3166_1":"NL","name":"Nederlands","english_name":"Dutch"},{"iso_639_1":"hu","iso_3166_1":"HU","name":"Magyar","english_name":"Hungarian"}]},"keywords":{"keywords":[]}}