{"adult":false,"backdrop_path":"/3FCnyxqVrjsM7VC6iCqnWmriY5e.jpg","belongs_to_collection":null,"budget":0,"genres":[{"id":35,"name":"Comedy"},{"id":10749,"name":"Romance"}],"homepage":"","id":46029,"imdb_id":"tt0118001","original_language":"en","original_title":"Two Much","overview":"A young gallerist is in love with two sisters at the same time. In order to solve the problem he decides to invent his own twin-brother.","popularity":0.15853,"poster_path":"/pTnIGNlRn0aLe4xWVLpXLsnDmt2.jpg","production_companies":[{"name":"PolyGram Filmed Entertainment","id":1382},{"name":"Lolafilms","id":6861},{"name":"Touchstone Pictures","id":9195},{"name":"Interscope Communications","id":10201},{"name":"Sociedad General de Televisión (Sogetel)","id":20295},{"name":"Fernando Trueba Producciones Cinematográficas","id":21108}],"production_countries":[{"iso_3166_1":"ES","name":"Spain"},{"iso_3166_1":"US","name":"United States of America"}],"release_date":"1996-02-14","revenue":0,"runtime":118,"spoken_languages":[{"iso_639_1":"en","name":"English"}],"status":"Released","tagline":"","title":"Two Much","video":false,"vote_average":5.0,"vote_count":18,"credits":{"cast":[{"cast_id":1,"character":"Art Dodge","credit_id":"52fe46e0c3a36847f81173e9","id":3131,"name":"Antonio Banderas","order":0,"profile_path":"/v4O21Uy3j5sKD4lR3DbYz2BnlIL.jpg"},{"cast_id":2,"character":"Betty","credit_id":"52fe46e0c3a36847f81173ed","id":29369,"name":"Melanie Griffith","order":1,"profile_path":"/cb2IeaETE0oVV5JZc79Vi0dS6m2.jpg"},{"cast_id":5,"character":"Liz","credit_id":"52fe46e0c3a36847f81173fd","id":589,"name":"Daryl Hannah","order":2,"profile_path":"/ekNHIbvMUa9MkLUmWMY9V3lmRqy.jpg"},{"cast_id":6,"character":"Gene","credit_id":"52fe46e0c3a36847f8117401","id":1004,"name":"Danny Aiello","order":3,"profile_path":"/UvPalkz4ynJJrTcrbpfD05gVoO.jpg"},{"cast_id":7,"character":"Gloria","credit_id":"52fe46e0c3a36847f8117405","id":3234,"name":"Joan Cusack","order":4,"profile_path":"/3jcrXcFYoSKEUvokzqrQ2UJGtw.jpg"},{"cast_id":8,"character":"Sheldon","credit_id":"52fe46e0c3a36847f8117409","id":3265,"name":"Eli Wallach","order":5,"profile_path":"/nRoyZzUjzY7iGdnp2V2kOgrMMFi.jpg"},{"cast_id":9,"character":"Manny","credit_id":"52fe46e0c3a36847f811740d","id":23215,"name":"Gabino Diego","order":6,"profile_path":"/qqAWyPU31uk6juPPP6YLHI6jr3a.jpg"},{"cast_id":12,"character":"Dr. Huffeyer","credit_id":"52fe46e0c3a36847f811741d","id":6168,"name":"Austin Pendleton","order":7,"profile_path":"/pxcdhd4oAsnhvUg0BalmiiKJyXg.jpg"},{"cast_id":13,"character":"Reverend Larrabee","credit_id":"52fe46e0c3a36847f8117421","id":568531,"name":"Allan Rich","order":8,"profile_path":"/Asmdc5LrKtjklKyWuEochYe3Rn2.jpg"},{"cast_id":14,"character":"Sommelier","credit_id":"52fe46e0c3a36847f8117425","id":3418,"name":"Vincent Schiavelli","order":9,"profile_path":"/9VAmZfthJ8pbDsJE8cJxIpnFcQy.jpg"},{"cast_id":15,"character":"Goon","credit_id":"52fe46e0c3a36847f8117429","id":84605,"name":"Jeff Moldovan","order":10,"profile_path":null},{"cast_id":16,"character":"Goon","credit_id":"52fe46e0c3a36847f811742d","id":84599,"name":"Joe Hess","order":11,"profile_path":null}],"crew":[{"credit_id":"52fe46e0c3a36847f81173f3","department":"Directing","id":37526,"job":"Director","name":"Fernando Trueba","profile_path":"/u0o8Oelx0KPL037RBxlNaB6G4Sa.jpg"},{"credit_id":"52fe46e0c3a36847f81173f9","department":"Writing","id":21672,"job":"Novel","name":"Donald E. Westlake","profile_path":"/tPbsbutxJU6tPeyZoOeJBe8ulzp.jpg"},{"credit_id":"52fe46e0c3a36847f8117413","department":"Writing","id":37526,"job":"Screenplay","name":"Fernando Trueba","profile_path":"/u0o8Oelx0KPL037RBxlNaB6G4Sa.jpg"},{"credit_id":"52fe46e0c3a36847f8117419","department":"Writing","id":59879,"job":"Screenplay","name":"David Trueba","profile_path":"/9kyyqY6N3DLI8A8pyqqjX8njDxZ.jpg"},{"credit_id":"576c9016c3a36830b8000b51","department":"Editing","id":1640578,"job":"Editor","name":"Nena Bernard","profile_path":null},{"credit_id":"576c901e9251411566001ce2","department":"Production","id":7731,"job":"Casting","name":"Elaine J. Huzzar","profile_path":null},{"credit_id":"576c903992514147e00009f8","department":"Art","id":1640579,"job":"Art Direction","name":"Carlos Arditti","profile_path":null},{"credit_id":"576c903fc3a3682459000ef3","department":"Art","id":1596655,"job":"Set Decoration","name":"Barbara Peterson-Malesci","profile_path":null},{"credit_id":"576c90279251414831000a9e","department":"Production","id":3686,"job":"Casting","name":"Johanna Ray","profile_path":null},{"credit_id":"576c902f9251411566001cf0","department":"Art","id":1027282,"job":"Production Design","name":"Juan Botella","profile_path":null},{"credit_id":"576c8eabc3a3682ff00008d7","department":"Sound","id":1062037,"job":"Original Music Composer","name":"Michel Camilo","profile_path":null},{"credit_id":"576c8eb4c3a3682f61000961","department":"Camera","id":4376,"job":"Director of Photography","name":"José Luis Alcaine","profile_path":null},{"credit_id":"576c90469251414831000acd","department":"Costume & Make-Up","id":16986,"job":"Costume Design","name":"Lala Huete","profile_path":null},{"credit_id":"576c9051c3a3682574000cfa","department":"Production","id":1640580,"job":"Unit Production Manager","name":"Ricky Sacco","profile_path":null}]},"release_dates":{"results":[{"iso_3166_1":"ES","release_dates":[{"certification":"","iso_639_1":"","note":"","release_date":"1996-12-01T00:00:00.000Z","type":3}]},{"iso_3166_1":"FR","release_dates":[{"certification":"","iso_639_1":"","note":"","release_date":"1996-06-05T00:00:00.000Z","type":3}]},{"iso_3166_1":"IT","release_dates":[{"certification":"","iso_639_1":"","release_date":"1996-02-14T00:00:00.000Z","type":3}]},{"iso_3166_1":"US","release_dates":[{"certification":"PG-13","iso_639_1":"","note":"","release_date":"1996-03-15T00:00:00.000Z","type":3}]}]},"alternative_titles":{"titles":[]},"translations":{"translations":[{"iso_639_1":"en","iso_3166_1":"US","name":"English","english_name":"English"},{"iso_639_1":"it","iso_3166_1":"IT","name":"Italiano","english_name":"Italian"},{"iso_639_1":"fr","iso_3166_1":"FR","name":"Français","english_name":"French"},{"iso_639_1":"hu","iso_3166_1":"HU","name":"Magyar","english_name":"Hungarian"},{"iso_639_1":"de","iso_3166_1":"DE","name":"Deutsch","english_name":"German"},{"iso_639_1":"ru","iso_3166_1":"RU","name":"Pусский","english_name":"Russian"},{"iso_639_1":"he","iso_3166_1":"IL","name":"עִבְרִית","english_name":"Hebrew"},{"iso_639_1":"es","iso_3166_1":"ES","name":"Español","english_name":"Spanish"},{"iso_639_1":"pt","iso_3166_1":"BR","name":"Português","english_name":"Portuguese"},{"iso_639_1":"cs","iso_3166_1":"CZ","name":"Český","english_name":"Czech"}]},"keywords":{"keywords":[]}}