{"results":[{"id":199933,"adult":false},{"id":295400,"adult":false},{"id":25037,"adult":false},{"id":130114,"adult":false},{"id":268171,"adult":false},{"id":317669,"adult":false},{"id":47697,"adult":false},{"id":288,"adult":false},{"id":27495,"adult":false},{"id":317670,"adult":false},{"id":233226,"adult":false},{"id":268,"adult":false},{"id":51528,"adult":false},{"id":26596,"adult":false},{"id":364,"adult":false},{"id":68299,"adult":false},{"id":63831,"adult":false},{"id":199423,"adult":false},{"id":14804,"adult":false},{"id":179621,"adult":false},{"id":272,"adult":false},{"id":263,"adult":false},{"id":120794,"adult":false},{"id":248534,"adult":false},{"id":317671,"adult":false},{"id":185738,"adult":false},{"id":268384,"adult":null},{"id":93236,"adult":false},{"id":32909,"adult":false},{"id":228350,"adult":false},{"id":54109,"adult":false},{"id":9960,"adult":false},{"id":40804,"adult":false},{"id":5735,"adult":false},{"id":44363,"adult":false},{"id":149232,"adult":false},{"id":134835,"adult":false},{"id":31297,"adult":false},{"id":70160,"adult":false},{"id":272157,"adult":false},{"id":48707,"adult":false},{"id":201414,"adult":false},{"id":47646,"adult":false},{"id":317672,"adult":false},{"id":317673,"adult":false},{"id":47370,"adult":false},{"id":312128,"adult":false},{"id":44800,"adult":false},{"id":299717,"adult":false},{"id":236189,"adult":false},{"id":317674,"adult":false},{"id":317675,"adult":false},{"id":283334,"adult":false},{"id":1246,"adult":false},{"id":317676,"adult":false},{"id":317677,"adult":false},{"id":317678,"adult":false},{"id":317679,"adult":false},{"id":317680,"adult":false},{"id":159402,"adult":false},{"id":317681,"adult":false},{"id":245891,"adult":false},{"id":227350,"adult":false},{"id":2080,"adult":false},{"id":317682,"adult":false},{"id":317683,"adult":false},{"id":2666,"adult":false},{"id":1410,"adult":false},{"id":51402,"adult":false},{"id":193604,"adult":false},{"id":9878,"adult":false},{"id":85446,"adult":false},{"id":317684,"adult":false},{"id":317685,"adult":false},{"id":12476,"adult":false},{"id":309038,"adult":false},{"id":26820,"adult":false},{"id":186920,"adult":false},{"id":8916,"adult":false},{"id":187533,"adult":false},{"id":85197,"adult":false},{"id":7861,"adult":false},{"id":8656,"adult":false},{"id":191386,"adult":false},{"id":288686,"adult":false},{"id":64992,"adult":false},{"id":42387,"adult":false},{"id":317686,"adult":false},{"id":15867,"adult":false},{"id":91065,"adult":false},{"id":120629,"adult":false},{"id":84760,"adult":false},{"id":990,"adult":false},{"id":279101,"adult":false},{"id":11227,"adult":false},{"id":85200,"adult":false},{"id":30644,"adult":false},{"id":5857,"adult":false},{"id":19794,"adult":false},{"id":292283,"adult":false}],"page":108,"total_pages":115,"total_results":11442}