{"results":[{"id":192210,"adult":false},{"id":9944,"adult":false},{"id":159664,"adult":false},{"id":38568,"adult":false},{"id":412253,"adult":false},{"id":412254,"adult":false},{"id":412255,"adult":false},{"id":82085,"adult":false},{"id":69206,"adult":false},{"id":126185,"adult":false},{"id":72262,"adult":false},{"id":9837,"adult":false},{"id":25539,"adult":false},{"id":30641,"adult":false},{"id":285116,"adult":false},{"id":17887,"adult":false},{"id":140300,"adult":false},{"id":11583,"adult":false},{"id":390782,"adult":false},{"id":218810,"adult":false},{"id":4421,"adult":false},{"id":412256,"adult":false},{"id":63611,"adult":false},{"id":3146,"adult":false},{"id":50830,"adult":false},{"id":404961,"adult":false},{"id":50856,"adult":false},{"id":48889,"adult":false},{"id":229346,"adult":false},{"id":11454,"adult":false},{"id":50907,"adult":false},{"id":46731,"adult":false},{"id":412257,"adult":false},{"id":412258,"adult":false},{"id":22244,"adult":false},{"id":412259,"adult":false},{"id":412260,"adult":false},{"id":49688,"adult":false},{"id":116982,"adult":false},{"id":39434,"adult":false},{"id":382399,"adult":false},{"id":45180,"adult":false},{"id":649,"adult":false},{"id":412261,"adult":false},{"id":56601,"adult":false},{"id":17367,"adult":false},{"id":49719,"adult":false},{"id":258509,"adult":false},{"id":58936,"adult":false},{"id":12445,"adult":false},{"id":265010,"adult":false},{"id":69778,"adult":false},{"id":54313,"adult":false},{"id":15143,"adult":false},{"id":977,"adult":false},{"id":55797,"adult":false},{"id":12912,"adult":false},{"id":14367,"adult":false},{"id":46850,"adult":false},{"id":390105,"adult":false},{"id":31819,"adult":false},{"id":276386,"adult":false},{"id":28651,"adult":false},{"id":279346,"adult":false},{"id":15324,"adult":false},{"id":68377,"adult":false},{"id":256561,"adult":false},{"id":6166,"adult":false},{"id":300566,"adult":false},{"id":279133,"adult":false},{"id":409843,"adult":false},{"id":376244,"adult":false},{"id":404954,"adult":null},{"id":11916,"adult":false},{"id":409995,"adult":false},{"id":25533,"adult":false},{"id":124597,"adult":false},{"id":409835,"adult":null},{"id":29117,"adult":false},{"id":72593,"adult":false},{"id":409669,"adult":false},{"id":412262,"adult":false},{"id":127560,"adult":false},{"id":49163,"adult":false},{"id":268771,"adult":false},{"id":211965,"adult":false},{"id":31074,"adult":false},{"id":42581,"adult":false},{"id":103079,"adult":false},{"id":412263,"adult":false},{"id":1686,"adult":false},{"id":366366,"adult":false},{"id":283108,"adult":false},{"id":57201,"adult":false},{"id":311667,"adult":false},{"id":321594,"adult":false},{"id":39276,"adult":false},{"id":35072,"adult":false},{"id":102715,"adult":false},{"id":48609,"adult":false}],"page":55,"total_pages":103,"total_results":10211}