{"results":[{"id":6183,"adult":false},{"id":9321,"adult":false},{"id":295940,"adult":false},{"id":389425,"adult":false},{"id":2749,"adult":false},{"id":404516,"adult":false},{"id":249474,"adult":false},{"id":4133,"adult":false},{"id":10786,"adult":false},{"id":97845,"adult":false},{"id":250696,"adult":false},{"id":288158,"adult":false},{"id":245168,"adult":false},{"id":360465,"adult":false},{"id":268178,"adult":false},{"id":299210,"adult":false},{"id":389053,"adult":false},{"id":265477,"adult":false},{"id":329967,"adult":false},{"id":262500,"adult":false},{"id":37960,"adult":false},{"id":72309,"adult":false},{"id":376569,"adult":false},{"id":404517,"adult":false},{"id":1359,"adult":false},{"id":380731,"adult":false},{"id":404518,"adult":false},{"id":274867,"adult":false},{"id":31661,"adult":false},{"id":81457,"adult":false},{"id":281255,"adult":false},{"id":1594,"adult":false},{"id":383262,"adult":false},{"id":44734,"adult":false},{"id":342588,"adult":false},{"id":211755,"adult":false},{"id":17165,"adult":false},{"id":15575,"adult":false},{"id":13398,"adult":false},{"id":119441,"adult":false},{"id":404519,"adult":false},{"id":37789,"adult":false},{"id":399833,"adult":null},{"id":81895,"adult":false},{"id":25278,"adult":false},{"id":404520,"adult":false},{"id":404521,"adult":false},{"id":255270,"adult":false},{"id":404522,"adult":null},{"id":276214,"adult":false},{"id":39323,"adult":false},{"id":404523,"adult":false},{"id":64784,"adult":false},{"id":186383,"adult":false},{"id":334927,"adult":false},{"id":334595,"adult":false},{"id":334207,"adult":false},{"id":315477,"adult":false},{"id":18837,"adult":false},{"id":352157,"adult":false},{"id":28697,"adult":false},{"id":297989,"adult":null},{"id":45970,"adult":false},{"id":335443,"adult":false},{"id":14132,"adult":false},{"id":330042,"adult":false},{"id":373522,"adult":false},{"id":73208,"adult":false},{"id":394520,"adult":false},{"id":263101,"adult":false},{"id":2008,"adult":false},{"id":44370,"adult":false},{"id":45966,"adult":false},{"id":120475,"adult":false},{"id":404524,"adult":false},{"id":16224,"adult":false},{"id":299963,"adult":false},{"id":361606,"adult":false},{"id":360600,"adult":false},{"id":360599,"adult":false},{"id":10165,"adult":false},{"id":404525,"adult":null},{"id":51678,"adult":false},{"id":335345,"adult":false},{"id":9521,"adult":false},{"id":18172,"adult":false},{"id":360601,"adult":false},{"id":51674,"adult":false},{"id":361609,"adult":false},{"id":360591,"adult":false},{"id":360607,"adult":false},{"id":360597,"adult":false},{"id":45314,"adult":false},{"id":297806,"adult":false},{"id":336543,"adult":false},{"id":51682,"adult":false},{"id":334411,"adult":false},{"id":333949,"adult":false},{"id":105734,"adult":false},{"id":9013,"adult":false}],"page":10,"total_pages":112,"total_results":11190}