{"results":[{"id":106138,"adult":false},{"id":174014,"adult":false},{"id":10851,"adult":false},{"id":283587,"adult":false},{"id":101233,"adult":false},{"id":398769,"adult":false},{"id":281661,"adult":false},{"id":241754,"adult":false},{"id":118792,"adult":false},{"id":19086,"adult":false},{"id":398770,"adult":false},{"id":398771,"adult":false},{"id":351232,"adult":false},{"id":347337,"adult":false},{"id":347339,"adult":false},{"id":25598,"adult":false},{"id":84273,"adult":false},{"id":16113,"adult":false},{"id":394856,"adult":false},{"id":316233,"adult":false},{"id":15379,"adult":false},{"id":12764,"adult":false},{"id":72923,"adult":false},{"id":395797,"adult":false},{"id":353491,"adult":false},{"id":55604,"adult":false},{"id":11307,"adult":false},{"id":620,"adult":false},{"id":11076,"adult":false},{"id":398772,"adult":false},{"id":2978,"adult":false},{"id":71340,"adult":false},{"id":316992,"adult":false},{"id":233451,"adult":false},{"id":398773,"adult":null},{"id":110733,"adult":false},{"id":120114,"adult":false},{"id":361346,"adult":false},{"id":88359,"adult":false},{"id":263115,"adult":false},{"id":338207,"adult":false},{"id":191812,"adult":false},{"id":20308,"adult":false},{"id":395766,"adult":false},{"id":19106,"adult":false},{"id":398774,"adult":false},{"id":398775,"adult":false},{"id":398776,"adult":false},{"id":398777,"adult":false},{"id":398778,"adult":false},{"id":398779,"adult":false},{"id":398780,"adult":false},{"id":398781,"adult":false},{"id":398782,"adult":false},{"id":50150,"adult":false},{"id":286371,"adult":false},{"id":27346,"adult":false},{"id":28945,"adult":false},{"id":24363,"adult":false},{"id":218670,"adult":false},{"id":63144,"adult":false},{"id":181132,"adult":false},{"id":81061,"adult":false},{"id":287284,"adult":false},{"id":328796,"adult":false},{"id":73846,"adult":false},{"id":24567,"adult":false},{"id":265973,"adult":false},{"id":857,"adult":false},{"id":17241,"adult":false},{"id":76354,"adult":false},{"id":398783,"adult":false},{"id":289261,"adult":false},{"id":300090,"adult":false},{"id":398784,"adult":false},{"id":66517,"adult":false},{"id":398785,"adult":false},{"id":264023,"adult":false},{"id":290597,"adult":false},{"id":11910,"adult":false},{"id":398786,"adult":false},{"id":32569,"adult":false},{"id":307624,"adult":false},{"id":398787,"adult":false},{"id":117092,"adult":false},{"id":23784,"adult":false},{"id":398788,"adult":false},{"id":80885,"adult":false},{"id":65266,"adult":false},{"id":279114,"adult":false},{"id":394595,"adult":false},{"id":347751,"adult":false},{"id":394600,"adult":false},{"id":394597,"adult":false},{"id":336029,"adult":false},{"id":394614,"adult":false},{"id":303312,"adult":false},{"id":394608,"adult":false},{"id":394593,"adult":false},{"id":395325,"adult":false}],"page":82,"total_pages":128,"total_results":12797}