{"results":[{"id":19281,"adult":false},{"id":363567,"adult":false},{"id":375831,"adult":false},{"id":356304,"adult":false},{"id":172466,"adult":false},{"id":122157,"adult":false},{"id":73465,"adult":false},{"id":370896,"adult":false},{"id":372554,"adult":false},{"id":371753,"adult":false},{"id":388583,"adult":false},{"id":365444,"adult":false},{"id":306470,"adult":false},{"id":191844,"adult":false},{"id":242262,"adult":false},{"id":390597,"adult":false},{"id":57052,"adult":false},{"id":375011,"adult":false},{"id":356631,"adult":false},{"id":91180,"adult":false},{"id":62024,"adult":false},{"id":240632,"adult":false},{"id":362789,"adult":false},{"id":372685,"adult":false},{"id":326121,"adult":false},{"id":311018,"adult":false},{"id":337186,"adult":false},{"id":290908,"adult":false},{"id":382411,"adult":false},{"id":271397,"adult":false},{"id":409099,"adult":false},{"id":399406,"adult":false},{"id":69728,"adult":false},{"id":404236,"adult":false},{"id":359748,"adult":false},{"id":360284,"adult":false},{"id":392202,"adult":false},{"id":413369,"adult":false},{"id":392203,"adult":false},{"id":122469,"adult":false},{"id":369367,"adult":false},{"id":390747,"adult":false},{"id":9440,"adult":false},{"id":396,"adult":false},{"id":354859,"adult":false},{"id":184572,"adult":false},{"id":291816,"adult":false},{"id":265094,"adult":false},{"id":415050,"adult":false},{"id":375991,"adult":false},{"id":267359,"adult":false},{"id":393694,"adult":false},{"id":11135,"adult":false},{"id":388843,"adult":false},{"id":409929,"adult":false},{"id":67957,"adult":false},{"id":176980,"adult":false},{"id":397122,"adult":false},{"id":160091,"adult":false},{"id":376731,"adult":false},{"id":415051,"adult":false},{"id":208668,"adult":false},{"id":324059,"adult":false},{"id":232865,"adult":false},{"id":360074,"adult":false},{"id":411536,"adult":false},{"id":132638,"adult":false},{"id":82011,"adult":false},{"id":377690,"adult":false},{"id":112154,"adult":false},{"id":196824,"adult":false},{"id":280952,"adult":false},{"id":299552,"adult":false},{"id":149416,"adult":false},{"id":258932,"adult":false},{"id":399864,"adult":false},{"id":18628,"adult":false},{"id":333598,"adult":false},{"id":200964,"adult":false},{"id":415052,"adult":false},{"id":295833,"adult":false},{"id":415053,"adult":false},{"id":3134,"adult":false},{"id":259556,"adult":false},{"id":394811,"adult":false},{"id":18875,"adult":false},{"id":367551,"adult":false},{"id":299556,"adult":false},{"id":359805,"adult":false},{"id":377933,"adult":false},{"id":330250,"adult":false},{"id":377961,"adult":false},{"id":389379,"adult":false},{"id":394772,"adult":false},{"id":398556,"adult":false},{"id":400526,"adult":false},{"id":380242,"adult":false},{"id":398565,"adult":false},{"id":398554,"adult":false},{"id":8055,"adult":false}],"page":87,"total_pages":126,"total_results":12554}