{"results":[{"id":12278,"adult":false},{"id":9605,"adult":false},{"id":29355,"adult":false},{"id":87872,"adult":false},{"id":9312,"adult":false},{"id":47474,"adult":false},{"id":306562,"adult":false},{"id":359983,"adult":false},{"id":248401,"adult":false},{"id":81858,"adult":true},{"id":124853,"adult":false},{"id":359984,"adult":true},{"id":359985,"adult":false},{"id":85378,"adult":null},{"id":281506,"adult":false},{"id":359568,"adult":false},{"id":294254,"adult":false},{"id":257015,"adult":false},{"id":359791,"adult":false},{"id":276846,"adult":false},{"id":161454,"adult":false},{"id":132338,"adult":false},{"id":244316,"adult":false},{"id":34854,"adult":false},{"id":296098,"adult":false},{"id":253863,"adult":false},{"id":4982,"adult":false},{"id":71741,"adult":false},{"id":356735,"adult":null},{"id":227722,"adult":null},{"id":359986,"adult":null},{"id":22074,"adult":false},{"id":157351,"adult":false},{"id":59429,"adult":false},{"id":359718,"adult":null},{"id":359987,"adult":false},{"id":303857,"adult":false},{"id":193580,"adult":false},{"id":240730,"adult":false},{"id":359472,"adult":null},{"id":348298,"adult":false},{"id":359988,"adult":false},{"id":10731,"adult":false},{"id":52681,"adult":false},{"id":86828,"adult":false},{"id":278901,"adult":false},{"id":55233,"adult":false},{"id":289727,"adult":false},{"id":359989,"adult":false},{"id":254128,"adult":false},{"id":102899,"adult":false},{"id":272693,"adult":false},{"id":353228,"adult":null},{"id":359597,"adult":null},{"id":62752,"adult":false},{"id":8467,"adult":false},{"id":264660,"adult":false},{"id":298303,"adult":true},{"id":211672,"adult":false},{"id":74997,"adult":false},{"id":265208,"adult":false},{"id":99861,"adult":false},{"id":218043,"adult":false},{"id":235986,"adult":null},{"id":359990,"adult":false},{"id":288575,"adult":null},{"id":338261,"adult":false},{"id":199615,"adult":false},{"id":63197,"adult":false},{"id":296367,"adult":false},{"id":146229,"adult":false},{"id":258947,"adult":false},{"id":168055,"adult":false},{"id":70707,"adult":false},{"id":290542,"adult":false},{"id":214439,"adult":false},{"id":6075,"adult":false},{"id":159446,"adult":false},{"id":359280,"adult":false},{"id":100046,"adult":false},{"id":269148,"adult":false},{"id":87358,"adult":false},{"id":15516,"adult":false},{"id":270178,"adult":false},{"id":86,"adult":false},{"id":216376,"adult":false},{"id":18887,"adult":false},{"id":196666,"adult":false},{"id":274369,"adult":false},{"id":75945,"adult":false},{"id":30874,"adult":false},{"id":359991,"adult":false},{"id":359992,"adult":false},{"id":345913,"adult":false},{"id":208597,"adult":false},{"id":7340,"adult":false},{"id":12488,"adult":false},{"id":116450,"adult":false},{"id":232450,"adult":false},{"id":71164,"adult":false}],"page":2,"total_pages":98,"total_results":9775}