{"results":[{"id":384013,"adult":false},{"id":16395,"adult":false},{"id":18983,"adult":false},{"id":297323,"adult":false},{"id":1678,"adult":false},{"id":814,"adult":false},{"id":9406,"adult":false},{"id":91549,"adult":false},{"id":125222,"adult":false},{"id":273153,"adult":false},{"id":24683,"adult":false},{"id":320048,"adult":false},{"id":9433,"adult":false},{"id":372939,"adult":false},{"id":49763,"adult":false},{"id":6488,"adult":false},{"id":384014,"adult":false},{"id":888,"adult":false},{"id":92804,"adult":false},{"id":5483,"adult":false},{"id":58151,"adult":false},{"id":21733,"adult":false},{"id":315244,"adult":false},{"id":190847,"adult":false},{"id":3603,"adult":false},{"id":184712,"adult":false},{"id":101820,"adult":false},{"id":4780,"adult":false},{"id":46020,"adult":false},{"id":22638,"adult":false},{"id":96343,"adult":false},{"id":224990,"adult":false},{"id":288338,"adult":false},{"id":123908,"adult":false},{"id":10075,"adult":false},{"id":44809,"adult":false},{"id":4290,"adult":false},{"id":209304,"adult":false},{"id":384015,"adult":false},{"id":341392,"adult":false},{"id":336843,"adult":false},{"id":47634,"adult":false},{"id":254584,"adult":false},{"id":9485,"adult":false},{"id":128311,"adult":false},{"id":55783,"adult":false},{"id":11807,"adult":false},{"id":77959,"adult":false},{"id":277305,"adult":false},{"id":240832,"adult":false},{"id":215056,"adult":false},{"id":384016,"adult":null},{"id":14071,"adult":false},{"id":384017,"adult":null},{"id":155949,"adult":false},{"id":133958,"adult":false},{"id":384018,"adult":false},{"id":19491,"adult":false},{"id":15774,"adult":false},{"id":44445,"adult":false},{"id":384019,"adult":false},{"id":57825,"adult":false},{"id":384020,"adult":false},{"id":22307,"adult":false},{"id":48923,"adult":false},{"id":192712,"adult":false},{"id":8453,"adult":false},{"id":1949,"adult":false},{"id":14214,"adult":false},{"id":57458,"adult":false},{"id":384021,"adult":false},{"id":50193,"adult":false},{"id":16576,"adult":false},{"id":21256,"adult":false},{"id":16608,"adult":false},{"id":20360,"adult":false},{"id":2268,"adult":false},{"id":8080,"adult":false},{"id":100088,"adult":false},{"id":382079,"adult":false},{"id":26277,"adult":false},{"id":302869,"adult":false},{"id":8892,"adult":false},{"id":75174,"adult":false},{"id":80035,"adult":false},{"id":263335,"adult":false},{"id":9770,"adult":false},{"id":384022,"adult":false},{"id":139262,"adult":false},{"id":377853,"adult":false},{"id":384023,"adult":false},{"id":159031,"adult":false},{"id":15730,"adult":false},{"id":4556,"adult":false},{"id":121157,"adult":false},{"id":384024,"adult":false},{"id":59762,"adult":false},{"id":83978,"adult":false},{"id":49768,"adult":false},{"id":308447,"adult":false}],"page":69,"total_pages":123,"total_results":12205}