{"results":[{"id":267185,"adult":false},{"id":355800,"adult":false},{"id":391117,"adult":null},{"id":348350,"adult":false},{"id":267186,"adult":false},{"id":41012,"adult":false},{"id":201967,"adult":false},{"id":82144,"adult":false},{"id":164593,"adult":false},{"id":74879,"adult":false},{"id":356136,"adult":false},{"id":129182,"adult":false},{"id":332788,"adult":false},{"id":300312,"adult":false},{"id":319341,"adult":false},{"id":218,"adult":false},{"id":391118,"adult":false},{"id":391119,"adult":false},{"id":267197,"adult":false},{"id":391120,"adult":false},{"id":369769,"adult":false},{"id":388254,"adult":null},{"id":391121,"adult":false},{"id":391122,"adult":false},{"id":117341,"adult":false},{"id":391123,"adult":false},{"id":335392,"adult":false},{"id":250861,"adult":false},{"id":206786,"adult":false},{"id":206789,"adult":false},{"id":391124,"adult":false},{"id":391125,"adult":true},{"id":317633,"adult":false},{"id":2344,"adult":false},{"id":206637,"adult":false},{"id":326775,"adult":false},{"id":302985,"adult":false},{"id":603,"adult":false},{"id":391126,"adult":false},{"id":114013,"adult":false},{"id":161420,"adult":false},{"id":58438,"adult":false},{"id":46373,"adult":false},{"id":1640,"adult":false},{"id":165573,"adult":false},{"id":290290,"adult":false},{"id":58441,"adult":false},{"id":279533,"adult":false},{"id":330,"adult":false},{"id":159,"adult":false},{"id":128207,"adult":false},{"id":40369,"adult":false},{"id":18988,"adult":false},{"id":391127,"adult":false},{"id":391128,"adult":false},{"id":46010,"adult":false},{"id":300622,"adult":false},{"id":337243,"adult":true},{"id":358144,"adult":false},{"id":29954,"adult":false},{"id":273894,"adult":false},{"id":195379,"adult":true},{"id":358138,"adult":false},{"id":359616,"adult":false},{"id":8580,"adult":false},{"id":306937,"adult":false},{"id":359617,"adult":false},{"id":359618,"adult":false},{"id":331280,"adult":null},{"id":286737,"adult":false},{"id":169607,"adult":false},{"id":366825,"adult":false},{"id":358142,"adult":false},{"id":359619,"adult":false},{"id":8340,"adult":false},{"id":218298,"adult":false},{"id":358140,"adult":false},{"id":359620,"adult":false},{"id":45781,"adult":false},{"id":338036,"adult":false},{"id":338247,"adult":true},{"id":167519,"adult":false},{"id":378180,"adult":false},{"id":311404,"adult":false},{"id":11293,"adult":false},{"id":85696,"adult":false},{"id":162057,"adult":false},{"id":323665,"adult":false},{"id":362478,"adult":false},{"id":65683,"adult":false},{"id":391129,"adult":false},{"id":1908,"adult":false},{"id":18780,"adult":false},{"id":108340,"adult":false},{"id":48612,"adult":false},{"id":391130,"adult":false},{"id":331288,"adult":false},{"id":161237,"adult":false},{"id":271826,"adult":false},{"id":391131,"adult":false}],"page":24,"total_pages":118,"total_results":11761}