{"adult":false,"backdrop_path":null,"belongs_to_collection":null,"budget":0,"genres":[{"id":28,"name":"Action"},{"id":53,"name":"Thriller"},{"id":80,"name":"Crime"},{"id":18,"name":"Drama"}],"homepage":"","id":109560,"imdb_id":"tt0117169","original_language":"en","original_title":"New York Cop","overview":"Allegedly based on a true story, this film follows the life of Toshi, a Japanese man living in America and working with the New York City police. After being recommended for undercover work, Toshi decides to go after a gang lead by Hawk. Hawk and Toshi soon become friends, although Hawk's second-in-command, Tito, is suspicious of the newcomer. Will Toshi be able to bring the gang down, or will his cover be blown before he can finish the assignment?","popularity":0.025159,"poster_path":"/hGJ3YlibjHNd9xP6rOIDTgh90eC.jpg","production_companies":[{"name":"TOEI","id":7260},{"name":"Distant Justice Joint Venture","id":42935}],"production_countries":[{"iso_3166_1":"JP","name":"Japan"},{"iso_3166_1":"US","name":"United States of America"}],"release_date":"1993-08-14","revenue":0,"runtime":93,"spoken_languages":[{"iso_639_1":"en","name":"English"},{"iso_639_1":"cn","name":"广州话 / 廣州話"}],"status":"Released","tagline":"The toughest city in the world deserves the toughest cop.","title":"New York Cop","video":false,"vote_average":0.0,"vote_count":0,"credits":{"cast":[{"cast_id":1,"character":"Toshi","credit_id":"52fe4abdc3a36847f81df2ef","id":74195,"name":"Toru Nakamura","order":0,"profile_path":"/gWoWSRKhnf5EPwQxbAMKFfZDeHT.jpg"},{"cast_id":2,"character":"Hawk","credit_id":"52fe4abdc3a36847f81df2f3","id":23920,"name":"Chad McQueen","order":1,"profile_path":"/bQxqP7npaJTSxhsNoaEllaYypwa.jpg"},{"cast_id":3,"character":"Maria","credit_id":"52fe4abdc3a36847f81df2f7","id":23931,"name":"Mira Sorvino","order":2,"profile_path":"/1BGJgCtqPYYclT2xMtH7zjbQ9r7.jpg"},{"cast_id":4,"character":"Konen Li","credit_id":"52fe4abdc3a36847f81df2fb","id":26783,"name":"Conan Lee","order":3,"profile_path":"/xAE76Nkhyqu7BLLTwz4z7w7kcRq.jpg"}],"crew":[{"credit_id":"54d5d7909251416b93001949","department":"Directing","id":129957,"job":"Director","name":"Tōru Murakawa","profile_path":null},{"credit_id":"54aa27ef9251415679000cf3","department":"Writing","id":66156,"job":"Writer","name":"Hiroshi Kashiwabara","profile_path":null},{"credit_id":"54aa27fa9251415646000cf5","department":"Writing","id":1409109,"job":"Story","name":"Jiro Ueno","profile_path":null}]},"release_dates":{"results":[{"iso_3166_1":"JP","release_dates":[{"certification":"","iso_639_1":"","note":"","release_date":"1993-08-14T00:00:00.000Z","type":3}]}]},"alternative_titles":{"titles":[{"iso_3166_1":"US","title":"New York Undercover Cop"},{"iso_3166_1":"JP","title":"Nyû Yôku U Koppu"}]},"translations":{"translations":[{"iso_639_1":"ja","iso_3166_1":"JP","name":"日本語","english_name":"Japanese"},{"iso_639_1":"en","iso_3166_1":"US","name":"English","english_name":"English"}]},"keywords":{"keywords":[]}}