{"adult":false,"backdrop_path":"/xW3LmKi99Rfz5FstvMen39c6MwO.jpg","belongs_to_collection":null,"budget":0,"genres":[{"id":10749,"name":"Romance"}],"homepage":"","id":280170,"imdb_id":"","original_language":"ta","original_title":"Sivappu","overview":"Konaar, the in-charge at a construction, takes in Sri Lankan refugees who have escaped from their welfare camp. Pandiyan, a worker, falls in love with Parvathy, a refugee. The couple elopes and Konaar seeks the help of a minister to unite them. But, the politician sees this incident as his only chance to win an election","popularity":0.015852,"poster_path":"/ppCkoAG2rui764VcFurmf5GLPhU.jpg","production_companies":[{"name":"Muktha Films","id":26634},{"name":"SG Films Pvt Ltd","id":26636}],"production_countries":[{"iso_3166_1":"IN","name":"India"}],"release_date":"2015-10-16","revenue":0,"runtime":0,"spoken_languages":[{"iso_639_1":"ta","name":"தமிழ்"}],"status":"Released","tagline":"","title":"Sivappu","video":false,"vote_average":5.0,"vote_count":2,"credits":{"cast":[{"cast_id":5,"character":"","credit_id":"53b5e3cd0e0a2676b8003e2e","id":1135117,"name":"Naveen Chandra","order":1,"profile_path":"/yzmdkTpS5X3Wl79uY5ZtfZIcpxn.jpg"},{"cast_id":6,"character":"","credit_id":"53b5e3d4c3a3685ec1001562","id":1099297,"name":"Rupa Manjari","order":2,"profile_path":"/kkqoQAWwQ5HsbYLI3fZuHpE5xfB.jpg"},{"cast_id":7,"character":"","credit_id":"53b5e4150e0a2676b8003e34","id":228287,"name":"Rajkiran","order":3,"profile_path":"/sIyVkGwf5QdrlByKPxMJdYP35Q3.jpg"},{"cast_id":8,"character":"","credit_id":"53b5e4470e0a2676c4003f4e","id":1114589,"name":"Thambi Ramaiah","order":4,"profile_path":"/471YOx1ZaX4mvUqHnqEmkXiKQRR.jpg"},{"cast_id":9,"character":"","credit_id":"53b5e44c0e0a2676c7004187","id":584471,"name":"A. Venkatesh","order":5,"profile_path":"/piyu7jLxRkxEcSLB4AeOUt7B2c1.jpg"},{"cast_id":10,"character":"","credit_id":"53b5e458c3a3685eb1001488","id":1337216,"name":"'Poo' Ram","order":6,"profile_path":null}],"crew":[{"credit_id":"53b5e3a70e0a2676cb003ea8","department":"Directing","id":1337213,"job":"Director","name":"Sathyashiva","profile_path":null},{"credit_id":"53b5e3adc3a3685ebd0014ff","department":"Sound","id":1124577,"job":"Music","name":"N. R. Raghunanthan","profile_path":null},{"credit_id":"53b5e3b10e0a2676cb003ead","department":"Production","id":1337214,"job":"Producer","name":"Muktha R. Govind","profile_path":null},{"credit_id":"53b5e3bb0e0a2676bf003ecf","department":"Crew","id":999159,"job":"Cinematography","name":"Madhu Ambat","profile_path":null},{"credit_id":"56250fd19251413ded0038df","department":"Writing","id":1065826,"job":"Writer","name":"Sathyasiva","profile_path":null},{"credit_id":"5678005192514179d20090e2","department":"Editing","id":544903,"job":"Editor","name":"Kasi Viswanathan","profile_path":"/w5myOjnHbjNtFFyHiqquzApqANL.jpg"}]},"release_dates":{"results":[{"iso_3166_1":"IN","release_dates":[{"certification":"U","iso_639_1":"","note":"","release_date":"2015-10-16T00:00:00.000Z","type":3}]}]},"alternative_titles":{"titles":[]},"translations":{"translations":[{"iso_639_1":"en","iso_3166_1":"US","name":"English","english_name":"English"}]},"keywords":{"keywords":[]}}